CVTLowpoly/__init__.py
CVTLowpoly/cvt_lloyd.py
CVTLowpoly/cvt_lowpoly.py
CVTLowpoly/fast_cvt_lowpoly.py
CVTLowpoly/jumping_flooding.py
CVTLowpoly/tri_raster.py
CVTLowpoly-1.0.2.dist-info/LICENSE
CVTLowpoly-1.0.2.dist-info/METADATA
CVTLowpoly-1.0.2.dist-info/WHEEL
CVTLowpoly-1.0.2.dist-info/top_level.txt
CVTLowpoly-1.0.2.dist-info/RECORD
