Metadata-Version: 2.1
Name: CVTLowpoly
Version: 1.0.2
Summary: A fast library for image lowpoly generation based on centroid voronoi diagram
Home-page: https://github.com/anapupa/PyCVTLowpoly
Author: Cong.Xie
Author-email: xiconxi@gmail.com
License: UNKNOWN
Project-URL: Bug Tracker, https://github.com/anapupa/PyCVTLowpoly/issues
Platform: UNKNOWN
Classifier: Programming Language :: Python :: 3
Classifier: License :: OSI Approved :: MIT License
Classifier: Operating System :: OS Independent
Requires-Python: >=3.6
License-File: LICENSE
Requires-Dist: taichi
Requires-Dist: taichi-glsl
Requires-Dist: scipy
Requires-Dist: opencv-python
Requires-Dist: numpy
